[
  {
    "Grupo": NaN,
    "GSO 2055-2": "Categoria",
    "Unnamed: 2": NaN,
    "Unnamed: 3": "Subcategoria",
    "Unnamed: 4": NaN,
    "SMIIC 2": "Categoria",
    "Unnamed: 6": NaN,
    "Unnamed: 7": "Subcategoria",
    "Unnamed: 8": NaN,
    "Formação": NaN,
    "Unnamed: 10": NaN,
    "Grupo.1": NaN,
    "GSO 2055-2.1": "Categoria",
    "Unnamed: 13": NaN,
    "Unnamed: 14": "Subcategoria",
    "SMIIC 2.1": "Categoria",
    "Unnamed: 16": NaN,
    "Unnamed: 17": "Subcategoria",
    "Unnamed: 18": NaN,
    "Formação.1": NaN
  },
  {
    "Grupo": "Agricultura",
    "GSO 2055-2": "A",
    "Unnamed: 2": "Criação de animais",
    "Unnamed: 3": "A I",
    "Unnamed: 4": "Criação de animais para produção de carne / leite / ovos / mel",
    "SMIIC 2": "A",
    "Unnamed: 6": "Criação de animais",
    "Unnamed: 7": "AI",
    "Unnamed: 8": "Criação de animais para produção de carne / leite / ovos / mel",
    "Formação": "Agronomia, Alimentos, Veterinária, Zootecnista",
    "Unnamed: 10": NaN,
    "Grupo.1": "Serviços auxiliares",
    "GSO 2055-2.1": "H",
    "Unnamed: 13": "Serviços",
    "Unnamed: 14": NaN,
    "SMIIC 2.1": "H",
    "Unnamed: 16": "Serviços",
    "Unnamed: 17": "HI",
    "Unnamed: 18": "Serviços relacionados com a segurança da produção de alimentos",
    "Formação.1": "Agronomia, Alimentos, Veterinária, Zootecnista"
  },
  {
    "Grupo": NaN,
    "GSO 2055-2": NaN,
    "Unnamed: 2": NaN,
    "Unnamed: 3": "A II",
    "Unnamed: 4": "Piscicultura/ produtos marinhos",
    "SMIIC 2": NaN,
    "Unnamed: 6": NaN,
    "Unnamed: 7": "AII",
    "Unnamed: 8": "Piscicultura/ produtos marinhos",
    "Formação": NaN,
    "Unnamed: 10": NaN,
    "Grupo.1": NaN,
    "GSO 2055-2.1": NaN,
    "Unnamed: 13": NaN,
    "Unnamed: 14": NaN,
    "SMIIC 2.1": NaN,
    "Unnamed: 16": NaN,
    "Unnamed: 17": NaN,
    "Unnamed: 18": NaN,
    "Formação.1": "Química,"
  },
  {
    "Grupo": NaN,
    "GSO 2055-2": "B",
    "Unnamed: 2": "Plantação agrícolas",
    "Unnamed: 3": "B I",
    "Unnamed: 4": "Cultivo de plantas (exceto leguminosas e grãos)",
    "SMIIC 2": "B",
    "Unnamed: 6": "Plantação de agrícolas",
    "Unnamed: 7": "BI",
    "Unnamed: 8": "Cultivo de plantas (exceto leguminosas e grãos)",
    "Formação": NaN,
    "Unnamed: 10": NaN,
    "Grupo.1": NaN,
    "GSO 2055-2.1": NaN,
    "Unnamed: 13": NaN,
    "Unnamed: 14": NaN,
    "SMIIC 2.1": NaN,
    "Unnamed: 16": NaN,
    "Unnamed: 17": NaN,
    "Unnamed: 18": NaN,
    "Formação.1": "Farmácia (se na grade tiverem matérias relacionadas a alimentos)"
  },
  {
    "Grupo": NaN,
    "GSO 2055-2": NaN,
    "Unnamed: 2": NaN,
    "Unnamed: 3": "B II",
    "Unnamed: 4": "Cultivo de leguminosas e grãos",
    "SMIIC 2": NaN,
    "Unnamed: 6": NaN,
    "Unnamed: 7": "BII",
    "Unnamed: 8": "Cultivo de leguminosas e grãos",
    "Formação": NaN,
    "Unnamed: 10": NaN,
    "Grupo.1": NaN,
    "GSO 2055-2.1": NaN,
    "Unnamed: 13": NaN,
    "Unnamed: 14": NaN,
    "SMIIC 2.1": NaN,
    "Unnamed: 16": NaN,
    "Unnamed: 17": "HII",
    "Unnamed: 18": "Serviços financeiros",
    "Formação.1": "Administração,"
  },
  {
    "Grupo": "Processamento de alimentos e rações",
    "GSO 2055-2": "C",
    "Unnamed: 2": "Produção de produtos alimentícios",
    "Unnamed: 3": "CI",
    "Unnamed: 4": "Processamento de produtos de origem animal perecível",
    "SMIIC 2": "C",
    "Unnamed: 6": "Produção de produtos alimentícios",
    "Unnamed: 7": "CI",
    "Unnamed: 8": "Abate Halal e",
    "Formação": "Agronomia, Alimentos, Veterinária, Zootecnista\nQuímica,\nFarmácia (se na grade tiverem matérias relacionadas a alimentos)",
    "Unnamed: 10": NaN,
    "Grupo.1": NaN,
    "GSO 2055-2.1": NaN,
    "Unnamed: 13": NaN,
    "Unnamed: 14": NaN,
    "SMIIC 2.1": NaN,
    "Unnamed: 16": NaN,
    "Unnamed: 17": NaN,
    "Unnamed: 18": NaN,
    "Formação.1": "Economia"
  },
  {
    "Grupo": NaN,
    "GSO 2055-2": NaN,
    "Unnamed: 2": NaN,
    "Unnamed: 3": NaN,
    "Unnamed: 4": NaN,
    "SMIIC 2": NaN,
    "Unnamed: 6": NaN,
    "Unnamed: 7": NaN,
    "Unnamed: 8": "Processamento de produtos perecíveis de origem animal",
    "Formação": NaN,
    "Unnamed: 10": NaN,
    "Grupo.1": NaN,
    "GSO 2055-2.1": NaN,
    "Unnamed: 13": NaN,
    "Unnamed: 14": NaN,
    "SMIIC 2.1": NaN,
    "Unnamed: 16": NaN,
    "Unnamed: 17": "HIII",
    "Unnamed: 18": "Turismo amigo do muçulmano (Muslim Friendly) e serviços relacionados a viagens",
    "Formação.1": "Agronomia, Alimentos, Veterinária, Zootecnista"
  },
  {
    "Grupo": NaN,
    "GSO 2055-2": NaN,
    "Unnamed: 2": NaN,
    "Unnamed: 3": "CII",
    "Unnamed: 4": "Processamento de produtos vegetais perecíveis",
    "SMIIC 2": NaN,
    "Unnamed: 6": NaN,
    "Unnamed: 7": "CII",
    "Unnamed: 8": "Processamento de produtos perecíveis de origem vegetal",
    "Formação": NaN,
    "Unnamed: 10": NaN,
    "Grupo.1": NaN,
    "GSO 2055-2.1": NaN,
    "Unnamed: 13": NaN,
    "Unnamed: 14": NaN,
    "SMIIC 2.1": NaN,
    "Unnamed: 16": NaN,
    "Unnamed: 17": NaN,
    "Unnamed: 18": NaN,
    "Formação.1": "Química,"
  },
  {
    "Grupo": NaN,
    "GSO 2055-2": NaN,
    "Unnamed: 2": NaN,
    "Unnamed: 3": "CIII",
    "Unnamed: 4": "Processamento de produtos perecíveis de origem animal e vegetal (produtos mistos)",
    "SMIIC 2": NaN,
    "Unnamed: 6": NaN,
    "Unnamed: 7": "CIII",
    "Unnamed: 8": "Processamento de produtos perecíveis de origem animal e vegetal (produtos cárneos, produtos mistos)",
    "Formação": NaN,
    "Unnamed: 10": NaN,
    "Grupo.1": NaN,
    "GSO 2055-2.1": "I",
    "Unnamed: 13": "Operações de embalagem e fabricação de materiais de embalagem",
    "Unnamed: 14": NaN,
    "SMIIC 2.1": "I",
    "Unnamed: 16": "Produção de embalagem para alimentos e de materiais de embalagem",
    "Unnamed: 17": NaN,
    "Unnamed: 18": NaN,
    "Formação.1": "Farmácia"
  },
  {
    "Grupo": NaN,
    "GSO 2055-2": NaN,
    "Unnamed: 2": NaN,
    "Unnamed: 3": "CIV",
    "Unnamed: 4": "Processamento de produtos estáveis ​​em temperatura ambiente",
    "SMIIC 2": NaN,
    "Unnamed: 6": NaN,
    "Unnamed: 7": "CIV",
    "Unnamed: 8": "Processamento de produtos estáveis ​​em temperatura ambiente",
    "Formação": NaN,
    "Unnamed: 10": NaN,
    "Grupo.1": NaN,
    "GSO 2055-2.1": "J",
    "Unnamed: 13": "Fabricação de equipamentos",
    "Unnamed: 14": NaN,
    "SMIIC 2.1": "J",
    "Unnamed: 16": "Fabricação de equipamentos",
    "Unnamed: 17": NaN,
    "Unnamed: 18": NaN,
    "Formação.1": "Engenharia"
  },
  {
    "Grupo": NaN,
    "GSO 2055-2": NaN,
    "Unnamed: 2": NaN,
    "Unnamed: 3": "CV",
    "Unnamed: 4": "Abate de animais",
    "SMIIC 2": NaN,
    "Unnamed: 6": NaN,
    "Unnamed: 7": "-",
    "Unnamed: 8": "-",
    "Formação": NaN,
    "Unnamed: 10": NaN,
    "Grupo.1": "Bioquímica",
    "GSO 2055-2.1": "K",
    "Unnamed: 13": "Fabricação de materiais bioquímicos",
    "Unnamed: 14": NaN,
    "SMIIC 2.1": "K",
    "Unnamed: 16": "Fabricação de materiais bioquímicos",
    "Unnamed: 17": NaN,
    "Unnamed: 18": NaN,
    "Formação.1": "Agronomia, Alimentos, Veterinária, Zootecnista"
  },
  {
    "Grupo": NaN,
    "GSO 2055-2": "D",
    "Unnamed: 2": "produção de ração animal",
    "Unnamed: 3": "DI",
    "Unnamed: 4": "produção de ração",
    "SMIIC 2": "D",
    "Unnamed: 6": "Produção de ração animal",
    "Unnamed: 7": "DI",
    "Unnamed: 8": "Produção de ração",
    "Formação": NaN,
    "Unnamed: 10": NaN,
    "Grupo.1": NaN,
    "GSO 2055-2.1": NaN,
    "Unnamed: 13": NaN,
    "Unnamed: 14": NaN,
    "SMIIC 2.1": NaN,
    "Unnamed: 16": NaN,
    "Unnamed: 17": NaN,
    "Unnamed: 18": NaN,
    "Formação.1": "Química,"
  },
  {
    "Grupo": NaN,
    "GSO 2055-2": NaN,
    "Unnamed: 2": NaN,
    "Unnamed: 3": "DII",
    "Unnamed: 4": "produção de ração dos animais de estimação",
    "SMIIC 2": NaN,
    "Unnamed: 6": NaN,
    "Unnamed: 7": "DII",
    "Unnamed: 8": "Produção de ração dos animais de estimação",
    "Formação": NaN,
    "Unnamed: 10": NaN,
    "Grupo.1": NaN,
    "GSO 2055-2.1": NaN,
    "Unnamed: 13": NaN,
    "Unnamed: 14": NaN,
    "SMIIC 2.1": NaN,
    "Unnamed: 16": NaN,
    "Unnamed: 17": NaN,
    "Unnamed: 18": NaN,
    "Formação.1": "Farmácia"
  },
  {
    "Grupo": "Servir o alimento",
    "GSO 2055-2": "E",
    "Unnamed: 2": "Servir o alimento",
    "Unnamed: 3": NaN,
    "Unnamed: 4": NaN,
    "SMIIC 2": "E",
    "Unnamed: 6": "Serviço de alimentação",
    "Unnamed: 7": NaN,
    "Unnamed: 8": NaN,
    "Formação": NaN,
    "Unnamed: 10": NaN,
    "Grupo.1": "-",
    "GSO 2055-2.1": NaN,
    "Unnamed: 13": NaN,
    "Unnamed: 14": NaN,
    "SMIIC 2.1": "L",
    "Unnamed: 16": "Outros materiais de processamento",
    "Unnamed: 17": "LI",
    "Unnamed: 18": "Cosméticos",
    "Formação.1": "Cosméticos,"
  },
  {
    "Grupo": "Distribuição de varejo, transporte, armazenamento",
    "GSO 2055-2": "F",
    "Unnamed: 2": "Distribuição",
    "Unnamed: 3": "FI",
    "Unnamed: 4": "Distribuição no atacado e varejo",
    "SMIIC 2": "F",
    "Unnamed: 6": "Distribuição",
    "Unnamed: 7": "FI",
    "Unnamed: 8": "Distribuição no atacado e varejo",
    "Formação": NaN,
    "Unnamed: 10": NaN,
    "Grupo.1": NaN,
    "GSO 2055-2.1": NaN,
    "Unnamed: 13": NaN,
    "Unnamed: 14": NaN,
    "SMIIC 2.1": NaN,
    "Unnamed: 16": NaN,
    "Unnamed: 17": NaN,
    "Unnamed: 18": NaN,
    "Formação.1": "Química,"
  },
  {
    "Grupo": NaN,
    "GSO 2055-2": NaN,
    "Unnamed: 2": NaN,
    "Unnamed: 3": "FII",
    "Unnamed: 4": "Operações de negociação e mediação",
    "SMIIC 2": NaN,
    "Unnamed: 6": NaN,
    "Unnamed: 7": "FII",
    "Unnamed: 8": "Operações de negociação e mediação",
    "Formação": NaN,
    "Unnamed: 10": NaN,
    "Grupo.1": NaN,
    "GSO 2055-2.1": NaN,
    "Unnamed: 13": NaN,
    "Unnamed: 14": NaN,
    "SMIIC 2.1": NaN,
    "Unnamed: 16": NaN,
    "Unnamed: 17": NaN,
    "Unnamed: 18": NaN,
    "Formação.1": "Farmácia"
  },
  {
    "Grupo": NaN,
    "GSO 2055-2": "G",
    "Unnamed: 2": "Termos de serviços de transporte armazenamento",
    "Unnamed: 3": "GI",
    "Unnamed: 4": "Termos de serviços de transporte armazenamento para alimentos e rações",
    "SMIIC 2": "G",
    "Unnamed: 6": "Fornecimento de serviços de transporte e armazenamento",
    "Unnamed: 7": "GI",
    "Unnamed: 8": "Locais de fornecimento de serviços de transporte e armazenamento para alimentos e rações perecíveis e estáveis à temperatura ambiente",
    "Formação": NaN,
    "Unnamed: 10": NaN,
    "Grupo.1": NaN,
    "GSO 2055-2.1": NaN,
    "Unnamed: 13": NaN,
    "Unnamed: 14": NaN,
    "SMIIC 2.1": NaN,
    "Unnamed: 16": NaN,
    "Unnamed: 17": "LII",
    "Unnamed: 18": "Têxteis e produtos têxteis",
    "Formação.1": "Engenharias diversas"
  },
  {
    "Grupo": NaN,
    "GSO 2055-2": NaN,
    "Unnamed: 2": NaN,
    "Unnamed: 3": "GII",
    "Unnamed: 4": "Locais de serviços de transporte e armazenamento de alimentos e rações fixos à temperatura ambiente",
    "SMIIC 2": NaN,
    "Unnamed: 6": NaN,
    "Unnamed: 7": "GII",
    "Unnamed: 8": "Locais de fornecimento de serviços de transporte e armazenamento para alimentos e rações estáveis à temperatura ambiente",
    "Formação": NaN,
    "Unnamed: 10": NaN,
    "Grupo.1": NaN,
    "GSO 2055-2.1": NaN,
    "Unnamed: 13": NaN,
    "Unnamed: 14": NaN,
    "SMIIC 2.1": NaN,
    "Unnamed: 16": NaN,
    "Unnamed: 17": "LIII",
    "Unnamed: 18": "Couro e derivados",
    "Formação.1": "Agronomia, Alimentos, Veterinária, Zootecnista"
  },
  {
    "Grupo": NaN,
    "GSO 2055-2": NaN,
    "Unnamed: 2": NaN,
    "Unnamed: 3": NaN,
    "Unnamed: 4": NaN,
    "SMIIC 2": NaN,
    "Unnamed: 6": NaN,
    "Unnamed: 7": NaN,
    "Unnamed: 8": NaN,
    "Formação": NaN,
    "Unnamed: 10": NaN,
    "Grupo.1": NaN,
    "GSO 2055-2.1": NaN,
    "Unnamed: 13": NaN,
    "Unnamed: 14": NaN,
    "SMIIC 2.1": NaN,
    "Unnamed: 16": NaN,
    "Unnamed: 17": NaN,
    "Unnamed: 18": NaN,
    "Formação.1": NaN
  },
  {
    "Grupo": NaN,
    "GSO 2055-2": NaN,
    "Unnamed: 2": NaN,
    "Unnamed: 3": NaN,
    "Unnamed: 4": NaN,
    "SMIIC 2": NaN,
    "Unnamed: 6": NaN,
    "Unnamed: 7": NaN,
    "Unnamed: 8": NaN,
    "Formação": NaN,
    "Unnamed: 10": NaN,
    "Grupo.1": NaN,
    "GSO 2055-2.1": NaN,
    "Unnamed: 13": NaN,
    "Unnamed: 14": NaN,
    "SMIIC 2.1": NaN,
    "Unnamed: 16": NaN,
    "Unnamed: 17": NaN,
    "Unnamed: 18": NaN,
    "Formação.1": NaN
  },
  {
    "Grupo": "Formação ",
    "GSO 2055-2": NaN,
    "Unnamed: 2": "GSO CATEGORIAS ",
    "Unnamed: 3": NaN,
    "Unnamed: 4": "SMIC CATEGORIAS",
    "SMIIC 2": NaN,
    "Unnamed: 6": NaN,
    "Unnamed: 7": NaN,
    "Unnamed: 8": NaN,
    "Formação": NaN,
    "Unnamed: 10": NaN,
    "Grupo.1": NaN,
    "GSO 2055-2.1": NaN,
    "Unnamed: 13": NaN,
    "Unnamed: 14": NaN,
    "SMIIC 2.1": NaN,
    "Unnamed: 16": NaN,
    "Unnamed: 17": NaN,
    "Unnamed: 18": NaN,
    "Formação.1": NaN
  },
  {
    "Grupo": "Agronomia, Alimentos, Veterinária, Zootecnista",
    "GSO 2055-2": NaN,
    "Unnamed: 2": "AI, AII, BI,BII, CI, CII, CIII, CIV, CV, DI, DII, E, FI, FII, GI, GII, HI, HIII, I e K",
    "Unnamed: 3": NaN,
    "Unnamed: 4": "AI, AII, BI,BII, CI, CII, CIII, CIV, DI, DII, E, FI, FII, GI, GII, HI, HIII, I, K e LIII",
    "SMIIC 2": NaN,
    "Unnamed: 6": NaN,
    "Unnamed: 7": NaN,
    "Unnamed: 8": NaN,
    "Formação": NaN,
    "Unnamed: 10": NaN,
    "Grupo.1": NaN,
    "GSO 2055-2.1": NaN,
    "Unnamed: 13": NaN,
    "Unnamed: 14": NaN,
    "SMIIC 2.1": NaN,
    "Unnamed: 16": NaN,
    "Unnamed: 17": NaN,
    "Unnamed: 18": NaN,
    "Formação.1": NaN
  },
  {
    "Grupo": "Química ",
    "GSO 2055-2": NaN,
    "Unnamed: 2": "CI, CII, CIII, CIV, CV, , DI, DII,FI, FII, GI, GII, I e K",
    "Unnamed: 3": NaN,
    "Unnamed: 4": "CI, CII, CIII, CIV, DI, DII, E, F, FII, GI, GII, HI, HIII, I,  K e LI",
    "SMIIC 2": NaN,
    "Unnamed: 6": NaN,
    "Unnamed: 7": NaN,
    "Unnamed: 8": NaN,
    "Formação": NaN,
    "Unnamed: 10": NaN,
    "Grupo.1": NaN,
    "GSO 2055-2.1": NaN,
    "Unnamed: 13": NaN,
    "Unnamed: 14": NaN,
    "SMIIC 2.1": NaN,
    "Unnamed: 16": NaN,
    "Unnamed: 17": NaN,
    "Unnamed: 18": NaN,
    "Formação.1": NaN
  },
  {
    "Grupo": "Farmácia ",
    "GSO 2055-2": NaN,
    "Unnamed: 2": "CI, CII, CIII, CIV, DI, DII, E, FI, FII, GI, GII, HI, HIII, I e K",
    "Unnamed: 3": NaN,
    "Unnamed: 4": "CI, CII, CIII, CIV, DI, DII, E, F, FII, GI, GII, HI, HIII, I,  K e LI",
    "SMIIC 2": NaN,
    "Unnamed: 6": NaN,
    "Unnamed: 7": NaN,
    "Unnamed: 8": NaN,
    "Formação": NaN,
    "Unnamed: 10": NaN,
    "Grupo.1": NaN,
    "GSO 2055-2.1": NaN,
    "Unnamed: 13": NaN,
    "Unnamed: 14": NaN,
    "SMIIC 2.1": NaN,
    "Unnamed: 16": NaN,
    "Unnamed: 17": NaN,
    "Unnamed: 18": NaN,
    "Formação.1": NaN
  }
]